PyDSS/NetworkModifier.py
PyDSS/ResultData.py
PyDSS/SolveMode.py
PyDSS/__init__.py
PyDSS/common.py
PyDSS/config_data.py
PyDSS/controllers.py
PyDSS/dataset_buffer.py
PyDSS/dssBus.py
PyDSS/dssCircuit.py
PyDSS/dssElement.py
PyDSS/dssElementFactory.py
PyDSS/dssInstance.py
PyDSS/dssObjectBase.py
PyDSS/dssTransformer.py
PyDSS/element_fields.py
PyDSS/element_options.py
PyDSS/exceptions.py
PyDSS/export_list_reader.py
PyDSS/get_snapshot_timepoints.py
PyDSS/helics_interface.py
PyDSS/loggers.py
PyDSS/metrics.py
PyDSS/naerm.py
PyDSS/node_voltage_metrics.py
PyDSS/pyContrReader.py
PyDSS/pyDSS.py
PyDSS/pyLogger.py
PyDSS/pyPlotReader.py
PyDSS/pyResults.py
PyDSS/pydss_fs_interface.py
PyDSS/pydss_project.py
PyDSS/pydss_results.py
PyDSS/registry.py
PyDSS/simulation_input_models.py
PyDSS/storage_filters.py
PyDSS/thermal_metrics.py
PyDSS/unitDefinations.py
PyDSS/value_storage.py
PyDSS/Extensions/MonteCarlo.py
PyDSS/Extensions/__init__.py
PyDSS/ProfileManager/ProfileInterface.py
PyDSS/ProfileManager/__init__.py
PyDSS/ProfileManager/base_definitions.py
PyDSS/ProfileManager/common.py
PyDSS/ProfileManager/hooks/MongoDB.py
PyDSS/ProfileManager/hooks/__init__.py
PyDSS/ProfileManager/hooks/h5.py
PyDSS/api/__init__.py
PyDSS/api/server.py
PyDSS/api/schema/__init__.py
PyDSS/api/src/__init__.py
PyDSS/api/src/app/DataWriter.py
PyDSS/api/src/app/HDF5.py
PyDSS/api/src/app/JSON_writer.py
PyDSS/api/src/app/Tester.py
PyDSS/api/src/app/__init__.py
PyDSS/api/src/app/pydss.py
PyDSS/api/src/web/__init__.py
PyDSS/api/src/web/create_schema.py
PyDSS/api/src/web/handler.py
PyDSS/api/src/web/parser.py
PyDSS/apps/__init__.py
PyDSS/apps/data_viewer.py
PyDSS/cli/__init__.py
PyDSS/cli/add_post_process.py
PyDSS/cli/add_scenario.py
PyDSS/cli/controllers.py
PyDSS/cli/convert.py
PyDSS/cli/create_project.py
PyDSS/cli/edit_scenario.py
PyDSS/cli/export.py
PyDSS/cli/extract.py
PyDSS/cli/pydss.py
PyDSS/cli/reports.py
PyDSS/cli/run.py
PyDSS/cli/run_server.py
PyDSS/defaults/__init__.py
PyDSS/defaults/plots.toml
dsspy-3.0.4.dist-info/LICENSE
dsspy-3.0.4.dist-info/METADATA
dsspy-3.0.4.dist-info/WHEEL
dsspy-3.0.4.dist-info/entry_points.txt
dsspy-3.0.4.dist-info/top_level.txt
dsspy-3.0.4.dist-info/RECORD
